octal8.py
octal8-1.2.1.dist-info/LICENSE
octal8-1.2.1.dist-info/METADATA
octal8-1.2.1.dist-info/WHEEL
octal8-1.2.1.dist-info/entry_points.txt
octal8-1.2.1.dist-info/top_level.txt
octal8-1.2.1.dist-info/RECORD
