Metadata-Version: 2.1
Name: octal8
Version: 1.2.1
Summary: Convert base-10 ints to base-8.
Home-page: https://github.com/samueljsb/octal8
Author: Samuel Searles-Bryant
Author-email: sam@samueljsb.co.uk
License: MIT
Platform: UNKNOWN
Classifier: License :: OSI Approved :: MIT License
Classifier: Programming Language :: Python :: 3
Classifier: Programming Language :: Python :: 3 :: Only
Classifier: Programming Language :: Python :: 3.7
Classifier: Programming Language :: Python :: 3.8
Classifier: Programming Language :: Python :: 3.9
Classifier: Programming Language :: Python :: 3.10
Classifier: Programming Language :: Python :: Implementation :: CPython
Requires-Python: >=3.7
License-File: LICENSE
Requires-Dist: tokenize-rt
